remoteAPI/__init__.py
remoteAPI/exceptions.py
remoteAPI/remote_api.py
remoteAPI-1.0.4.dist-info/DESCRIPTION.rst
remoteAPI-1.0.4.dist-info/METADATA
remoteAPI-1.0.4.dist-info/RECORD
remoteAPI-1.0.4.dist-info/WHEEL
remoteAPI-1.0.4.dist-info/metadata.json
remoteAPI-1.0.4.dist-info/top_level.txt
