Metadata-Version: 2.0
Name: remoteAPI
Version: 1.0.4
Summary: A wrapper for python requests package customized to use in PISHKHAN
Home-page: https://github.com/mohibeyki/remoteAPI.git
Author: Mohi Beyki
Author-email: mohi@cafebazaar.ir
License: UNKNOWN
Download-URL: https://github.com/mohibeyki/remoteAPI/archive/1.0.4.tar.gz
Keywords: pishkhan,cafebazaar,remote
Platform: UNKNOWN
